[{"run_id": 9223370488180900307, "name": "run from keep", "distance": 3027.102112496983, "moving_time": "0:16:52", "type": "Run", "start_date": "2019-01-28 10:47:06", "start_date_local": "2019-01-28 18:47:06", "location_country": "{'latitude': 39.903081868489586, 'longitude': 116.23795084635417, 'country': '\u4e2d\u56fd', 'nationCode': '156', 'province': '\u5317\u4eac\u5e02', 'city': '\u5317\u4eac\u5e02', 'cityCode': '010', 'district': None, 'districtCode': None}", "summary_polyline": null, "average_heartrate": null, "average_speed": 2.9912076210444494, "streak": 1}, {"run_id": 9223370488005606807, "name": "run from keep", "distance": 3034.402415834945, "moving_time": "0:16:19", "type": "Run", "start_date": "2019-01-30 11:30:06", "start_date_local": "2019-01-30 19:30:06", "location_country": "{'latitude': 39.90313802083333, 'longitude': 116.23831814236111, 'country': '\u4e2d\u56fd', 'nationCode': '156', 'province': '\u5317\u4eac\u5e02', 'city': '\u5317\u4eac\u5e02', 'cityCode': '010', 'district': None, 'districtCode': None}", "summary_polyline": null, "average_heartrate": null, "average_speed": 3.0994917424258883, "streak": 1}, {"run_id": 9223370486960588607, "name": "run from keep", "distance": 3045.2170708221097, "moving_time": "0:15:11", "type": "Run", "start_date": "2019-02-11 13:49:56", "start_date_local": "2019-02-11 21:49:56", "location_country": "{'latitude': 39.9032115342882, 'longitude': 116.23805094401041, 'country': '\u4e2d\u56fd', 'nationCode': '156', 'province': '\u5317\u4eac\u5e02', 'city': '\u5317\u4eac\u5e02', 'cityCode': '010', 'district': None, 'districtCode': None}", "summary_polyline": null, "average_heartrate": null, "average_speed": 3.342719067861811, "streak": 1}, {"run_id": 9223370486790504507, "name": "run from keep", "distance": 3013.8599069712886, "moving_time": "0:16:58", "type": "Run", "start_date": "2019-02-13 13:06:07", "start_date_local": "2019-02-13 21:06:07", "location_country": "{'latitude': 39.90324327256945, 'longitude': 116.2379966905382, 'country': '\u4e2d\u56fd', 'nationCode': '156', 'province': '\u5317\u4eac\u5e02', 'city': '\u5317\u4eac\u5e02', 'cityCode': '010', 'district': None, 'districtCode': None}", "summary_polyline": null, "average_heartrate": null, "average_speed": 2.9605696532134465, "streak": 1}, {"run_id": 9223370486532704307, "name": "run from keep", "distance": 3106.490231108058, "moving_time": "0:17:20", "type": "Run", "start_date": "2019-02-16 12:39:24", "start_date_local": "2019-02-16 20:39:24", "location_country": "{'latitude': 39.903592393663196, 'longitude': 116.23737114800348, 'country': '\u4e2d\u56fd', 'nationCode': '156', 'province': '\u5317\u4eac\u5e02', 'city': '\u5317\u4eac\u5e02', 'cityCode': '010', 'district': None, 'districtCode': None}", "summary_polyline": null, "average_heartrate": null, "average_speed": 2.9870098376039023, "streak": 1}, {"run_id": 9223370486358840907, "name": "run from keep", "distance": 3037.566352718279, "moving_time": "0:15:52", "type": "Run", "start_date": "2019-02-18 13:01:27", "start_date_local": "2019-02-18 21:01:27", "location_country": "{'latitude': 39.90329861111111, 'longitude': 116.23793863932292, 'country': '\u4e2d\u56fd', 'nationCode': '156', 'province': '\u5317\u4eac\u5e02', 'city': '\u5317\u4eac\u5e02', 'cityCode': '010', 'district': None, 'districtCode': None}", "summary_polyline": null, "average_heartrate": null, "average_speed": 3.190720958737688, "streak": 1}, {"run_id": 9223370486097929407, "name": "run from keep", "distance": 3110.4197622025763, "moving_time": "0:15:11", "type": "Run", "start_date": "2019-02-21 13:30:21", "start_date_local": "2019-02-21 21:30:21", "location_country": "{'latitude': 39.902939453125, 'longitude': 116.2361021592882, 'country': '\u4e2d\u56fd', 'nationCode': '156', 'province': '\u5317\u4eac\u5e02', 'city': '\u5317\u4eac\u5e02', 'cityCode': '010', 'district': None, 'districtCode': None}", "summary_polyline": null, "average_heartrate": null, "average_speed": 3.4142917257986567, "streak": 1}, {"run_id": 9223370486011740407, "name": "run from keep", "distance": 3032.0261872613073, "moving_time": "0:16:22", "type": "Run", "start_date": "2019-02-22 13:25:54", "start_date_local": "2019-02-22 21:25:54", "location_country": "{'latitude': 39.903422309027775, 'longitude': 116.23806884765625, 'country': '\u4e2d\u56fd', 'nationCode': '156', 'province': '\u5317\u4eac\u5e02', 'city': '\u5317\u4eac\u5e02', 'cityCode': '010', 'district': None, 'districtCode': None}", "summary_polyline": null, "average_heartrate": null, "average_speed": 3.0876030420176246, "streak": 2}, {"run_id": 9223370473313011207, "name": "run from keep", "distance": 2048.6788347048637, "moving_time": "0:10:49", "type": "Run", "start_date": "2019-07-19 12:58:30", "start_date_local": "2019-07-19 20:58:30", "location_country": "{'latitude': 39.90276421440972, 'longitude': 116.23696912977431, 'country': '\u4e2d\u56fd', 'nationCode': '156', 'province': '\u5317\u4eac\u5e02', 'city': '\u5317\u4eac\u5e02', 'cityCode': '010', 'district': None, 'districtCode': None}", "summary_polyline": "oeprFoildUzBoBAe@GcAQ{@FoA`@Uh@Ev@aGAWYq@Q?c@Fa@FUCq@@W?k@Hi@AqAvB[fAC^HvAAhBCh@Dr@Xx@PTZ^JLFLr@JlAq@v@mAEoCDe@x@}@L?r@m@Ak@Cg@Dk@Hk@]uAM?gACmBHa@?MAS@k@Do@d@?V?pBCn@C`AFz@Gl@EZPxCPT", "average_heartrate": null, "average_speed": 3.1566700072494047, "streak": 1}, {"run_id": 9223370472362077707, "name": "run from keep", "distance": 2057.754163425632, "moving_time": "0:10:44", "type": "Run", "start_date": "2019-07-30 13:07:28", "start_date_local": "2019-07-30 21:07:28", "location_country": "{'latitude': 39.903285319010415, 'longitude': 116.23921847873264, 'country': '\u4e2d\u56fd', 'nationCode': '156', 'province': '\u5317\u4eac\u5e02', 'city': '\u5317\u4eac\u5e02', 'cityCode': '010', 'district': None, 'districtCode': None}", "summary_polyline": "whprFqjldUJH~BWv@o@H}ABu@@[Ec@tAcAXc@C_B@w@GsBCUy@CWEi@EUE_AHm@J_BpASbBIl@@r@Bt@AX@dAE`BRl@pA~AXbARS`@_Ar@@|@b@Dp@@RX~@ZYWgEe@wCdAcCf@_AAYBu@Bq@B]?u@A[qB@g@@Q@e@Mc@CWBu@?WCi@`@?p@AZCP", "average_heartrate": null, "average_speed": 3.1952704401019134, "streak": 1}, {"run_id": 9223370472270663307, "name": "run from keep", "distance": 2031.5228227676791, "moving_time": "0:10:05", "type": "Run", "start_date": "2019-07-31 14:31:45", "start_date_local": "2019-07-31 22:31:45", "location_country": "{'latitude': 39.90317545572917, 'longitude': 116.2397252061632, 'country': '\u4e2d\u56fd', 'nationCode': '156', 'province': '\u5317\u4eac\u5e02', 'city': '\u5317\u4eac\u5e02', 'cityCode': '010', 'district': None, 'districtCode': None}", "summary_polyline": "}hprFklldUi@h@F]zANtDrACp@Ri@S_AEe@CeA?w@QoClAs@~@_@Aa@Aw@E[@}@BWc@kAIGeAXWBsBGaABy@nB?^IhAERP~BBVHfDTNJFDH\\VVJn@V~@q@P@h@}@IwAAUCs@A]d@s@XC~@{@Eq@Gu@Bu@SyAs@Gs@AkADM?IIo@Bk@J", "average_heartrate": null, "average_speed": 3.3578889632523623, "streak": 2}, {"run_id": 9223370472099895007, "name": "run from keep", "distance": 2033.2104431505265, "moving_time": "0:09:43", "type": "Run", "start_date": "2019-08-02 13:58:14", "start_date_local": "2019-08-02 21:58:14", "location_country": "{'latitude': 39.90328396267361, 'longitude': 116.23965169270834, 'country': '\u4e2d\u56fd', 'nationCode': '156', 'province': '\u5317\u4eac\u5e02', 'city': '\u5317\u4eac\u5e02', 'cityCode': '010', 'district': None, 'districtCode': None}", "summary_polyline": "qgprFamldUPDhB|@h@?PjB?LC_@K}DB]?eARiCHWf@AVDv@gAGiAA_AA_@o@oAm@Ca@?OFqFvAGxAHRKvASl@Ht@JfA?PD|@r@tAZA`DVZq@I{@@w@?WDs@dAwAT?j@}AQu@G}@B]E{@c@GoBLo@M_DN", "average_heartrate": null, "average_speed": 3.487496471956306, "streak": 1}, {"run_id": 9223370472017131507, "name": "run from keep", "distance": 2036.1769022636938, "moving_time": "0:09:15", "type": "Run", "start_date": "2019-08-03 12:58:07", "start_date_local": "2019-08-03 20:58:07", "location_country": "{'latitude': 39.90310546875, 'longitude': 116.23968315972222, 'country': '\u4e2d\u56fd', 'nationCode': '156', 'province': '\u5317\u4eac\u5e02', 'city': '\u5317\u4eac\u5e02', 'cityCode': '010', 'district': None, 'districtCode': None}", "summary_polyline": "eeprFiildUuAUjBzAtBWCCq@iCI{@KeAfAyCtA}BDw@H]D}@Aw@A@GDY@aA@q@@WGS@eB@{@SGB[bCc@xE@RJxAA\\Jd@b@Rl@z@t@\\LB~AGJPVkBIU]eBvAmBZAb@m@?kBAiACs@BQMUWB}AP[\\EKu@Aq@B}@L", "average_heartrate": null, "average_speed": 3.668787211285935, "streak": 2}, {"run_id": 9223370471843331307, "name": "run from keep", "distance": 2043.7336665257667, "moving_time": "0:08:57", "type": "Run", "start_date": "2019-08-05 13:15:00", "start_date_local": "2019-08-05 21:15:00", "location_country": "{'latitude': 39.90307156032986, 'longitude': 116.24016927083333, 'country': '\u4e2d\u56fd', 'nationCode': '156', 'province': '\u5317\u4eac\u5e02', 'city': '\u5317\u4eac\u5e02', 'cityCode': '010', 'district': None, 'districtCode': None}", "summary_polyline": "kdprFaoldUy@zC^d@ReF|ArC@F@eAWyEjBeAb@[?S@{@@_@CcAa@cBGAqAR{@CWG{@?i@A}@vBLjCIv@A\\Et@CTExA?Zl@|AN?v@f@tCgBCaBEu@DsAz@g@n@@TCAaBBYBqAEUWi@ADB@cACkBAeAOo@D", "average_heartrate": null, "average_speed": 3.8058355056345747, "streak": 1}, {"run_id": 9223370471757533307, "name": "run from keep", "distance": 2040.16211854095, "moving_time": "0:10:21", "type": "Run", "start_date": "2019-08-06 13:03:40", "start_date_local": "2019-08-06 21:03:40", "location_country": "{'latitude': 39.903218587239586, 'longitude': 116.23825032552084, 'country': '\u4e2d\u56fd', 'nationCode': '156', 'province': '\u5317\u4eac\u5e02', 'city': '\u5317\u4eac\u5e02', 'cityCode': '010', 'district': None, 'districtCode': None}", "summary_polyline": "ifprFykldUt@[NAhA_@N}AEwB`Au@`@iB?{@?Ya@{By@@cARI?g@?kBTu@IUxC?v@Ax@@XFr@BV@x@C\\Az@R~@PNd@VNBz@b@PB\\sAb@Rb@tAGVF_B@YDaA?aAA_@A{@@UT}@N@N@x@q@Ea@FsA]uCo@NYBg@BQ?OBO@aAOSFu@@IEm@d@AVKrBCT@j@D^Dr@?P", "average_heartrate": null, "average_speed": 3.2852852150417875, "streak": 2}, {"run_id": 9223370471671390407, "name": "run from keep", "distance": 2037.061816597552, "moving_time": "0:10:04", "type": "Run", "start_date": "2019-08-07 12:59:39", "start_date_local": "2019-08-07 20:59:39", "location_country": "{'latitude': 39.903212890625, 'longitude': 116.23798177083333, 'country': '\u4e2d\u56fd', 'nationCode': '156', 'province': '\u5317\u4eac\u5e02', 'city': '\u5317\u4eac\u5e02', 'cityCode': '010', 'district': None, 'districtCode': None}", "summary_polyline": "qjprFinldUf@bBd@LdCO\\F\\m@DWEcC~@sCfAi@DYH}@B]_AsCiBFQAm@?YAi@@u@AM?i@RWfAI~A?pAD`@JdACr@?dAFr@d@n@^Nl@~@N^G@BAvBeABqBFWWyBd@Wp@a@l@Ml@}BL[Ni@BQwCsAYAe@CW@o@?W@u@AOBO@a@^Mp@Ah@i@xA^|C", "average_heartrate": null, "average_speed": 3.372618901651576, "streak": 3}, {"run_id": 9223370471544136307, "name": "run from keep", "distance": 2003.973680693394, "moving_time": "0:10:10", "type": "Run", "start_date": "2019-08-09 00:20:16", "start_date_local": "2019-08-09 08:20:16", "location_country": "{'latitude': 39.90325141059028, 'longitude': 116.23809705946181, 'country': '\u4e2d\u56fd', 'nationCode': '156', 'province': '\u5317\u4eac\u5e02', 'city': '\u5317\u4eac\u5e02', 'cityCode': '010', 'district': None, 'districtCode': None}", "summary_polyline": "shprF}jldU`A^fDsBA[Gs@AYI{@xByCBeAEeB@_@_@e@WE{A?Q?o@?q@Cq@?GAiApBAREjC?ZBnA?v@APAt@@TVhAVP\\^pB\\n@aAPBh@aBkB_ABY?IaAsAbCgBCUEYEw@CkAs@gAUBa@@GEg@DUBc@JYhA@n@@ZAp@B^\\jC@BEV", "average_heartrate": null, "average_speed": 3.285202755235072, "streak": 1}, {"run_id": 9223370471459698207, "name": "run from keep", "distance": 2035.8678460841404, "moving_time": "0:10:32", "type": "Run", "start_date": "2019-08-09 23:47:24", "start_date_local": "2019-08-10 07:47:24", "location_country": "{'latitude': 39.90333062065972, 'longitude': 116.23808213975694, 'country': '\u4e2d\u56fd', 'nationCode': '156', 'province': '\u5317\u4eac\u5e02', 'city': '\u5317\u4eac\u5e02', 'cityCode': '010', 'district': None, 'districtCode': None}", "summary_polyline": "{dprF_lldUKmAAOAWG{@Ya@OGw@OOgARCn@CbBF`@yBMyACq@Fo@]Es@QaBHU?c@bBB|@@`AAjA@VIfACv@B~@@TXdAPRf@d@LPf@TXCpA_Ah@_BYg@QCaAm@eAaBp@KXIx@sACm@@[BeACi@Ck@k@[i@Ae@DULs@O]r@EvB@\\Cd@B~@MdB", "average_heartrate": null, "average_speed": 3.221309883044526, "streak": 2}, {"run_id": 9223370471325283207, "name": "run from keep", "distance": 2028.370813082768, "moving_time": "0:09:59", "type": "Run", "start_date": "2019-08-11 13:08:12", "start_date_local": "2019-08-11 21:08:12", "location_country": "{'latitude': 39.90276584201389, 'longitude': 116.23864501953125, 'country': '\u4e2d\u56fd', 'nationCode': '156', 'province': '\u5317\u4eac\u5e02', 'city': '\u5317\u4eac\u5e02', 'cityCode': '010', 'district': None, 'districtCode': None}", "summary_polyline": "mcprF{kldUP?r@}@EWOyB@sAZ]V?f@?l@k@XeBASEcAI]kAm@_AE[Bk@Bi@Ci@?[BeBl@Ft@Cb@At@IxBN~@@XAxAB^vAzBz@f@tAkATBTe@Ow@_@[OCm@S^yCn@m@EcBB_@Cq@?Uq@y@oADo@?UEy@YF`@@rAB^ChAAN", "average_heartrate": null, "average_speed": 3.386261791457042, "streak": 3}, {"run_id": 9223370471200394407, "name": "run from keep", "distance": 1211.099030370249, "moving_time": "0:06:08", "type": "Run", "start_date": "2019-08-12 23:52:59", "start_date_local": "2019-08-13 07:52:59", "location_country": "{'latitude': 39.90178493923611, 'longitude': 116.23725206163195, 'country': '\u4e2d\u56fd', 'nationCode': '156', 'province': '\u5317\u4eac\u5e02', 'city': '\u5317\u4eac\u5e02', 'cityCode': '010', 'district': None, 'districtCode': None}", "summary_polyline": null, "average_heartrate": null, "average_speed": 3.2910299738321984, "streak": 1}, {"run_id": 9223370471110837507, "name": "run from keep", "distance": 1039.6333303499555, "moving_time": "0:05:18", "type": "Run", "start_date": "2019-08-14 00:46:54", "start_date_local": "2019-08-14 08:46:54", "location_country": "{'latitude': 39.903171929253475, 'longitude': 116.23801703559027, 'country': '\u4e2d\u56fd', 'nationCode': '156', 'province': '\u5317\u4eac\u5e02', 'city': '\u5317\u4eac\u5e02', 'cityCode': '010', 'district': None, 'districtCode': None}", "summary_polyline": "ehprFckldULRXTRJdB{@p@aAAeAq@Dq@u@@KBOm@g@K_Bh@FbA{@@iACW?}@Bc@Qg@c@Mw@@u@Fi@Gi@bB?n@@VBv@b@dDOJCR", "average_heartrate": null, "average_speed": 3.269287202358351, "streak": 2}, {"run_id": 9223370470978507307, "name": "run from keep", "distance": 2026.5914977383475, "moving_time": "0:10:03", "type": "Run", "start_date": "2019-08-15 13:27:44", "start_date_local": "2019-08-15 21:27:44", "location_country": "{'latitude': 39.903177625868054, 'longitude': 116.23831759982639, 'country': '\u4e2d\u56fd', 'nationCode': '156', 'province': '\u5317\u4eac\u5e02', 'city': '\u5317\u4eac\u5e02', 'cityCode': '010', 'district': None, 'districtCode': None}", "summary_polyline": "gjprFcoldU@^^Pl@f@rCNt@s@?w@e@G}CcC~CsBA]Eu@Cc@?s@o@wAYAyAD}AlAL|@BVB`AEpB@h@@f@AXf@`CZRfB|@jAu@PAPkAE[Eo@?gBfA}@|@gBAu@By@e@_BU?a@?S@c@DSAk@?_AAm@B_@?u@MCNB~@AdABx@B\\Fv@", "average_heartrate": null, "average_speed": 3.3608482549558003, "streak": 3}, {"run_id": 9223370470853551807, "name": "run from keep", "distance": 1046.963119160032, "moving_time": "0:05:08", "type": "Run", "start_date": "2019-08-17 00:15:11", "start_date_local": "2019-08-17 08:15:11", "location_country": "{'latitude': 39.903132866753474, 'longitude': 116.23748291015625, 'country': '\u4e2d\u56fd', 'nationCode': '156', 'province': '\u5317\u4eac\u5e02', 'city': '\u5317\u4eac\u5e02', 'cityCode': '010', 'district': None, 'districtCode': None}", "summary_polyline": null, "average_heartrate": null, "average_speed": 3.3992309063637403, "streak": 1}, {"run_id": 9223370470635281507, "name": "run from keep", "distance": 1050.5947113458437, "moving_time": "0:05:13", "type": "Run", "start_date": "2019-08-19 12:52:59", "start_date_local": "2019-08-19 20:52:59", "location_country": "{'latitude': 39.903050130208335, 'longitude': 116.23785888671875, 'country': '\u4e2d\u56fd', 'nationCode': '156', 'province': '\u5317\u4eac\u5e02', 'city': '\u5317\u4eac\u5e02', 'cityCode': '010', 'district': None, 'districtCode': None}", "summary_polyline": "ohprFslldUh@TtAh@^WZCl@qAEWIw@?_@?u@h@cBTB~@c@PeAJk@Iw@cD}Ag@?M@cAKOAg@FaAG_@?BZLhAHfADx@HtB", "average_heartrate": null, "average_speed": 3.356532624108127, "streak": 1}, {"run_id": 9223370456553064707, "name": "run from keep", "distance": 1238.7917216450387, "moving_time": "0:06:52", "type": "Run", "start_date": "2020-01-29 12:34:54", "start_date_local": "2020-01-29 20:34:54", "location_country": "{'latitude': 39.90335611979167, 'longitude': 116.23953125, 'country': '\u4e2d\u56fd', 'nationCode': '156', 'province': '\u5317\u4eac\u5e02', 'city': '\u5317\u4eac\u5e02', 'cityCode': '010', 'district': None, 'districtCode': None}", "summary_polyline": "chprFijldUNPhB{BAo@?YI_Be@qAEQtBAJD|@BPD`@BJuBAWBq@AOG}Bg@GSAoBHmAyAMc@Ys@Ug@V_BiB|@AZK|A@\\?l@Tx@DZETQt@KP", "average_heartrate": null, "average_speed": 3.0067760234102883, "streak": 1}, {"run_id": 9223370456396198307, "name": "run from keep", "distance": 748.2153691980916, "moving_time": "0:05:25", "type": "Run", "start_date": "2020-01-31 08:10:42", "start_date_local": "2020-01-31 16:10:42", "location_country": "{'latitude': 39.903255479600695, 'longitude': 116.23811631944444, 'country': '\u4e2d\u56fd', 'nationCode': '156', 'province': '\u5317\u4eac\u5e02', 'city': '\u5317\u4eac\u5e02', 'cityCode': '010', 'district': None, 'districtCode': None}", "summary_polyline": "wbprFeuldUx@BT@f@A\\wAQeD[}AQBm@@S?oB[UAi@DiAjBEVDFA@BDBDDDDFFBBT@CA@DBAPIXCJ?FCHGJC\\E^AFCJARCFANIZAFCLERATPGEK", "average_heartrate": null, "average_speed": 2.302201135994128, "streak": 1}, {"run_id": 9223370439525810807, "name": "run from keep", "distance": 3064.26806640625, "moving_time": "0:19:32", "type": "Run", "start_date": "2020-08-13 14:09:53", "start_date_local": "2020-08-13 07:09:53", "location_country": "{'latitude': 37.880685, 'longitude': -122.294274, 'country': '\u7f8e\u56fd', 'nationCode': '840', 'province': None, 'city': None, 'cityCode': None, 'district': None, 'districtCode': None}", "summary_polyline": null, "average_heartrate": null, "average_speed": 2.6145631965923637, "streak": 1}, {"run_id": 9223370439438636807, "name": "run from keep", "distance": 3813.482177734375, "moving_time": "0:21:56", "type": "Run", "start_date": "2020-08-14 14:20:23", "start_date_local": "2020-08-14 07:20:23", "location_country": "{'latitude': 37.880685, 'longitude': -122.294274, 'country': '\u7f8e\u56fd', 'nationCode': '840', 'province': None, 'city': None, 'cityCode': None, 'district': None, 'districtCode': None}", "summary_polyline": null, "average_heartrate": null, "average_speed": 2.8977828098285525, "streak": 2}, {"run_id": 9223370438752171807, "name": "run from keep", "distance": 2203.82958984375, "moving_time": "0:18:52", "type": "Run", "start_date": "2020-08-22 13:04:32", "start_date_local": "2020-08-22 06:04:32", "location_country": "{'latitude': 37.880685, 'longitude': -122.294274, 'country': '\u7f8e\u56fd', 'nationCode': '840', 'province': None, 'city': None, 'cityCode': None, 'district': None, 'districtCode': None}", "summary_polyline": null, "average_heartrate": null, "average_speed": 1.9468459274238075, "streak": 1}, {"run_id": 9223370438575322807, "name": "run from keep", "distance": 4011.369384765625, "moving_time": "0:31:31", "type": "Run", "start_date": "2020-08-24 13:59:21", "start_date_local": "2020-08-24 06:59:21", "location_country": "{'latitude': 37.880685, 'longitude': -122.294274, 'country': '\u7f8e\u56fd', 'nationCode': '840', 'province': None, 'city': None, 'cityCode': None, 'district': None, 'districtCode': None}", "summary_polyline": null, "average_heartrate": null, "average_speed": 2.1212952854392517, "streak": 1}, {"run_id": 9223370436427217807, "name": "run from keep", "distance": 4049.3916015625, "moving_time": "0:21:55", "type": "Run", "start_date": "2020-09-18 10:50:42", "start_date_local": "2020-09-18 03:50:42", "location_country": "{'latitude': 37.880685, 'longitude': -122.294274, 'country': '\u7f8e\u56fd', 'nationCode': '840', 'province': None, 'city': None, 'cityCode': None, 'district': None, 'districtCode': None}", "summary_polyline": null, "average_heartrate": null, "average_speed": 3.079385248336502, "streak": 1}, {"run_id": 9223370423928848807, "name": "run from keep", "distance": 1585.4144287109375, "moving_time": "1:00:38", "type": "Run", "start_date": "2021-02-08 12:46:56", "start_date_local": "2021-02-08 05:46:56", "location_country": "{'latitude': 37.880685, 'longitude': -122.294274, 'country': '\u7f8e\u56fd', 'nationCode': '840', 'province': None, 'city': None, 'cityCode': None, 'district': None, 'districtCode': None}", "summary_polyline": null, "average_heartrate": null, "average_speed": 0.4357928611080092, "streak": 1}, {"run_id": 9223370381208952807, "name": "run from keep", "distance": 1587.7259083187832, "moving_time": "0:09:54", "type": "Run", "start_date": "2022-06-19 13:21:47", "start_date_local": "2022-06-19 21:21:47", "location_country": "{'latitude': 39.89849351895668, 'longitude': 116.24287633682528, 'country': '\u4e2d\u56fd', 'nationCode': '156', 'province': '\u5317\u4eac\u5e02', 'city': '\u5317\u4eac\u5e02', 'cityCode': '010', 'district': '\u4e30\u53f0\u533a', 'districtCode': '110106'}", "summary_polyline": "kjprFwnldU[j@e@B_@j@ApAQ~@@h@p@r@^?^?NANA\\AJ@J?`@?P?`@@nAHf@?`ACN?p@BN@NA`@EX?j@?LAL@v@CLAL@\\BL?L?X?H?r@EP@z@ETAd@@NAd@ELCJA^Eb@CZK\\GZs@AS?SA]?OAOAGAe@?OAQEsABu@@YBe@?Q@SAg@?O?QAa@@]Go@?O@[Bc@@[Bc@?s@?MAO?OA_@?iAAUEUAm@AUuA}EG@IB[@u@F", "average_heartrate": null, "average_speed": 2.6729392395939113, "streak": 1}, {"run_id": 9223370380089009907, "name": "run from keep", "distance": 1840.260366659986, "moving_time": "0:11:38", "type": "Run", "start_date": "2022-07-02 12:29:16", "start_date_local": "2022-07-02 20:29:16", "location_country": "{'latitude': 39.90271809973038, 'longitude': 116.24032156269597, 'country': '\u4e2d\u56fd', 'nationCode': '156', 'province': '\u5317\u4eac\u5e02', 'city': '\u5317\u4eac\u5e02', 'cityCode': '010', 'district': '\u6d77\u6dc0\u533a', 'districtCode': '110108'}", "summary_polyline": "kjprFarldU?g@@W@o@?o@AcD@c@?YFmAJw@Fa@r@{AN@L?`@?^MLKLIVWHITS|@MN^HLN^HNX|@JhCO`ABf@B^?N?VGh@Cb@Ad@g@h@[CMAg@BM?[@O@MAI@@As@F_@EQA_@Aw@h@@REvBA|@d@|@`@f@JLHJ`@PN?f@_AAi@b@mAL@XAX_A@g@Ai@?O?MX_@N@JAL?T?\\g@BSA_@AM?cAAc@Aq@@KCQQOM@Q?]AeA@k@?o@BGAg@?", "average_heartrate": null, "average_speed": 2.63647616999998, "streak": 1}, {"run_id": 9223370379828434307, "name": "run from keep", "distance": 3021.239045533553, "moving_time": "0:19:41", "type": "Run", "start_date": "2022-07-05 12:45:58", "start_date_local": "2022-07-05 20:45:58", "location_country": "{'latitude': 39.90369172282479, 'longitude': 116.24426572421832, 'country': '\u4e2d\u56fd', 'nationCode': '156', 'province': '\u5317\u4eac\u5e02', 'city': '\u5317\u4eac\u5e02', 'cityCode': '010', 'district': '\u6d77\u6dc0\u533a', 'districtCode': '110108'}", "summary_polyline": null, "average_heartrate": null, "average_speed": 2.558204102907327, "streak": 1}, {"run_id": 9223370379650338307, "name": "run from keep", "distance": 3000.0, "moving_time": "0:19:41", "type": "Run", "start_date": "2022-07-07 14:14:11", "start_date_local": "2022-07-07 22:14:11", "location_country": "{'latitude': 39.90368605343026, 'longitude': 116.24434826469651, 'country': '\u4e2d\u56fd', 'nationCode': '156', 'province': '\u5317\u4eac\u5e02', 'city': '\u5317\u4eac\u5e02', 'cityCode': '010', 'district': '\u6d77\u6dc0\u533a', 'districtCode': '110108'}", "summary_polyline": null, "average_heartrate": null, "average_speed": 2.5402201524132093, "streak": 1}, {"run_id": 9223370379391860407, "name": "run from keep", "distance": 3022.0423552006146, "moving_time": "0:19:20", "type": "Run", "start_date": "2022-07-10 14:01:46", "start_date_local": "2022-07-10 22:01:46", "location_country": "{'latitude': 39.903691886569206, 'longitude': 116.24369372728209, 'country': '\u4e2d\u56fd', 'nationCode': '156', 'province': '\u5317\u4eac\u5e02', 'city': '\u5317\u4eac\u5e02', 'cityCode': '010', 'district': '\u6d77\u6dc0\u533a', 'districtCode': '110108'}", "summary_polyline": "ijprFsnldU?X~@fAFPl@j@^h@?n@?`@Nj@pAJN?b@?v@EX@j@BRAd@E`A?tA?N?dBBNALAr@BfBI~@Ix@KPCjBmA?s@@S?Q?i@AOCy@Ac@?SAU@i@@c@?S?O?m@?o@?U?Y?o@?UAm@@W@cBAW@q@AmACq@?s@Aq@?m@@[Bi@AUAWCm@AW@WAq@?mA@Y?Q@o@@[Bo@CcAAY@y@?iAAWAq@@g@A_AA[@k@AeA@U?UAcA?Y?i@AU?UwAcAe@COAoA@S@cA?yA?Q?OCe@@O@O?a@BQAI@c@?OAO@kAA_@?O?m@?Q?OAc@@M?Q@a@?OCa@BQ?Q?a@@QAOAc@?w@@Q@M?g@@Sh@?T@VAl@AR?X?h@@V?RAp@BR?R?n@?RANBfAAR?VAn@?V?P?x@@f@?T?T@l@?X?j@?R?R", "average_heartrate": null, "average_speed": 2.6052089268970815, "streak": 1}, {"run_id": 9223370378872997307, "name": "run from keep", "distance": 2087.8608498133103, "moving_time": "0:13:15", "type": "Run", "start_date": "2022-07-16 14:13:13", "start_date_local": "2022-07-16 22:13:13", "location_country": "{'latitude': 39.899012588861076, 'longitude': 116.24889979410152, 'country': '\u4e2d\u56fd', 'nationCode': '156', 'province': '\u5317\u4eac\u5e02', 'city': '\u5317\u4eac\u5e02', 'cityCode': '010', 'district': '\u6d77\u6dc0\u533a', 'districtCode': '110108'}", "summary_polyline": null, "average_heartrate": null, "average_speed": 2.626240062658252, "streak": 1}, {"run_id": 9223370378010319607, "name": "run from keep", "distance": 3028.5937236410855, "moving_time": "0:19:43", "type": "Run", "start_date": "2022-07-26 13:47:51", "start_date_local": "2022-07-26 21:47:51", "location_country": "{'latitude': 39.90369853440954, 'longitude': 116.24541419379221, 'country': '\u4e2d\u56fd', 'nationCode': '156', 'province': '\u5317\u4eac\u5e02', 'city': '\u5317\u4eac\u5e02', 'cityCode': '010', 'district': '\u6d77\u6dc0\u533a', 'districtCode': '110108'}", "summary_polyline": "clprFmdldUl@CtAAbA@PAL?Z@L?L?^?L?N?^@L?h@AL@LA^?N@J?`@?N@h@EP?L@\\AL?N@X?LAj@@t@AN?dBAPAr@IJ?XAL?LEZCNCHA|@OTSDa@?SAO?c@@O?Q?c@CW@U?kB?Y@o@Ao@AY?w@?O?O?k@@O?Q?u@?QAS?c@?O?QAO@e@AOAS@c@Ai@Ak@AY@o@AWBo@BS?o@Ek@E_B?aA?m@?OAY@c@?O?a@?U?M?M@c@?Q?S?a@AQ?O@QAc@?c@?s@AQDa@?QAg@@O?SAa@?o@?{@?U?W?g@?W?Y@g@AO?QU}@Q?a@?Q?MAc@CiCAMBQ?_@BO?O?c@AeA?[?e@BO?I?M?W?c@AMAK?W?KAK@I@U?M@K?I?WAKAK@M@S?MAY@a@AM?I?iA?K@MA[?K?K@MAW?Y@M?I?I?u@|@CNAp@?NC^?b@?L?d@BP?b@@NAX@`A@`A?X?PAxA", "average_heartrate": null, "average_speed": 2.5600961315647384, "streak": 1}, {"run_id": 9223370377840344207, "name": "run from keep", "distance": 1064.3353053711426, "moving_time": "0:05:52", "type": "Run", "start_date": "2022-07-28 13:14:34", "start_date_local": "2022-07-28 21:14:34", "location_country": "{'latitude': 39.90161131065119, 'longitude': 116.23607673581148, 'country': '\u4e2d\u56fd', 'nationCode': '156', 'province': '\u5317\u4eac\u5e02', 'city': '\u5317\u4eac\u5e02', 'cityCode': '010', 'district': '\u4e30\u53f0\u533a', 'districtCode': '110106'}", "summary_polyline": "mhprFqkldU\\p@NXl@jBATxATb@?r@@v@BPC|@CL?b@?xAFV?f@@L?`AFNAJ?\\?LANAVAL?NE^?h@CKIODQ@q@HO?O@yBBQ@aACSA[@O?W?]?s@G[AM@a@AO?", "average_heartrate": null, "average_speed": 3.0236798448043825, "streak": 1}, {"run_id": 9223370374413547307, "name": "run from keep", "distance": 1316.7898154518086, "moving_time": "0:07:28", "type": "Run", "start_date": "2022-09-06 05:06:20", "start_date_local": "2022-09-05 22:06:20", "location_country": "{'latitude': 37.880696468194984, 'longitude': -122.29452445985615, 'country': '\u7f8e\u56fd', 'nationCode': '840', 'province': None, 'city': None, 'cityCode': None, 'district': None, 'districtCode': None}", "summary_polyline": "_qefFhpliVnAQj@Kd@KREd@IPIh@Ib@lALn@BRHp@BVHl@_AbAi@LQF{@PWFaATeAiAIq@CYGk@CUIi@Z{@^KRCb@KNEJC\\G^I\\KPEb@IPERJFn@Jp@Fl@DVFl@DVw@tAg@Na@HOFw@NQDc@HODODg@UCUGg@AQCSM}@", "average_heartrate": null, "average_speed": 2.939262980919216, "streak": 1}, {"run_id": 9223370365613905607, "name": "run from keep", "distance": 1565.0635739040713, "moving_time": "0:10:41", "type": "Run", "start_date": "2022-12-17 01:23:49", "start_date_local": "2022-12-16 18:23:49", "location_country": "{'latitude': 37.88032336113877, 'longitude': -122.29384432543584, 'country': '\u7f8e\u56fd', 'nationCode': '840', 'province': None, 'city': None, 'cityCode': None, 'district': None, 'districtCode': None}", "summary_polyline": "onefFbpliVNEnA_@XEp@MVGZE`@KLEd@MTGj@KPEl@MREtA[PEf@KREh@MNEh@MLCh@MPEn@MVG`@K`@IREd@KPEd@KNE`@KbAYPEv@QP?g@M]HOFOD]HMBKBq@JQBODYJODK@a@HODMD]FMDMBEDg@JaAT]DOFM@aAXKDm@PMBOBgAL]HMBMBYHKBOBu@NIBKBKBq@LKDI@KDWDKDK@MDYFK@QFE@[F", "average_heartrate": null, "average_speed": 2.4415968391639176, "streak": 1}, {"run_id": 9223370365272517407, "name": "run from keep", "distance": 1636.7566331974688, "moving_time": "0:11:20", "type": "Run", "start_date": "2022-12-21 00:12:51", "start_date_local": "2022-12-20 17:12:51", "location_country": "{'latitude': 37.88472149880917, 'longitude': -122.29526709681625, 'country': '\u7f8e\u56fd', 'nationCode': '840', 'province': None, 'city': None, 'cityCode': None, 'district': None, 'districtCode': None}", "summary_polyline": "krefFlpliVqBn@UFeE~@WDeCd@UDiB`@OD_BXw@Ns@Xc@FQDc@F{A^KDQB_@JQFa@DMDQF[F_@BS@u@ZQBc@JoAVODMBa@HQBOD_@JMBm@NOBKB]HK@OF_@JMBGDp@QNELG^INCLG^INANE\\KNCLCb@MNCNAZKLCJAXILEZGJCLCVI\\GNCNC^ILCNE\\Gt@QLELCZIJCNAXILCLE\\GJEp@MJCHA", "average_heartrate": null, "average_speed": 2.406995048819807, "streak": 1}, {"run_id": 9223370364995306107, "name": "run from keep", "distance": 3021.489549803186, "moving_time": "0:24:10", "type": "Run", "start_date": "2022-12-24 05:00:16", "start_date_local": "2022-12-23 22:00:16", "location_country": "{'latitude': 37.8806425911945, 'longitude': -122.29406002988794, 'country': '\u7f8e\u56fd', 'nationCode': '840', 'province': None, 'city': None, 'cityCode': None, 'district': None, 'districtCode': None}", "summary_polyline": "}nefF~oliVh@Kr@SNCNC\\GPGlAUNId@KPGNC\\GJCJELC^INEPA^Ml@MNENC`@ILEb@KNENAr@Sp@ONEt@ONELC\\Kp@GNGNE`@OPCNE`@G^ILCPCn@QLEPE^K@@UFODQDMB]FYF_@FMFMB[Fm@NK@ODk@PM@OD]F]Am@PODOBYHMBM@I@YL[FMBMD[DMFMB]FKBMBYFo@JOFKD]HMDM@w@RMBMBIBm@FcAXMFKBYF[FKBMBIB[HMDMB]FMBMDi@D]JMDIBk@JKFMBYFMBMB[HQBKD]HMBMD[DMD]FMDOB[HM@OD[HMDOB[FMB[HMDOF]DMDMB[DMDMDYFK@MB_@HMBMB[HKBO@[LK@KDUDI@MFMB]FMDMD[FMDMB[FYFMD`@GLAZIJCXGLCJGZEHCVGLEJAXGXKZEJCLEf@GLEJCHCZGLAVGLEh@OHALEJCREJCJCHCTGLENAJCVGJEJAVGJAf@If@QL?LEXIJ?XMXAPIHCHCJCXGJCZGLEHALC\\GNC", "average_heartrate": null, "average_speed": 2.0837858964159905, "streak": 1}, {"run_id": 9223370364056598807, "name": "run from keep", "distance": 3511.1162292708077, "moving_time": "0:29:22", "type": "Run", "start_date": "2023-01-04 01:39:16", "start_date_local": "2023-01-03 18:39:16", "location_country": "{'latitude': 37.88004897826759, 'longitude': -122.29386757850807, 'country': '\u7f8e\u56fd', 'nationCode': '840', 'province': None, 'city': None, 'cityCode': None, 'district': None, 'districtCode': None}", "summary_polyline": "gqefFjrliVb@_Af@ORCh@Mf@MrBc@~@MNCn@OPEPE^KNC`@IPEn@SLG`@I^G`@ILCNA\\INCLCZILCNE\\IHg@AA}Br@MB[J]FYHMBMD]FKDQB[FMDOECQE_@Ec@]c@g@w@OGMC]KMEKCICUGOCy@AOZHh@Hh@@PBRJx@BPBRFd@BRBRFf@BRBRFd@BR@Tg@JYJ]HK@KD[@MDMD[H[FOBMD]JMBSAEe@ESAMGq@i@_@WHo@NKBIBKBWHKBK@KBa@FKBIBKBWDMBIBe@Nc@NKBIDW@b@ENI^MJENC\\IJCLCZIPELEp@INEJE^KLCf@KREJGRNV@HCJCHCVGJCLEHCZEJCLEJC^KJAJCJC\\[a@HK@MB_ATKDo@DKBKBIBWF]DRTZEHCJCXEJEJAd@WLCJC\\I\\Cb@IXc@C@m@NKDYFKBI@KBUHKBK@IBg@HGBI@KDWDOBUFGTDH\\KHARGLGJAJCTGNEJAHEXGXGJATEJGHANCVINALCXGHANCJCVKLCJC`@INCNGHAP]_@BKBUJEBM?MBWFMDE@QBG@WH[J_@NKBc@BKBMBIBYFKBWDc@Rm@JO?[DBZXELCJC\\INCLCZIIA", "average_heartrate": null, "average_speed": 1.9926879848301973, "streak": 1}, {"run_id": 9223370363805735807, "name": "run from keep", "distance": 2274.332633260454, "moving_time": "0:16:53", "type": "Run", "start_date": "2023-01-06 23:31:16", "start_date_local": "2023-01-06 16:31:16", "location_country": "{'latitude': 37.87681007894681, 'longitude': -122.29359675090504, 'country': '\u7f8e\u56fd', 'nationCode': '840', 'province': None, 'city': None, 'cityCode': None, 'district': None, 'districtCode': None}", "summary_polyline": "eqefFhrliVdAaApA_@tAYh@Oz@MREb@Kt@W|@e@f@a@Ey@COKu@l@MPCb@K`@KLEPC^ILCLE^ILCNC^Ib@KJCtAw@XQEQAe@Cg@ESAOE_@_A`@kAPKBg@PBQG_AAOAQAOEq@ASCQC_@ASAOEg@Ly@Ee@?SAQ?]C?CSIc@GOESM]AOGMKc@GQEOK_@EQGSK_@GOb@_APILI\\OX@LHVVFPHLXRVBNNAVF\\Dj@@TDdB@h@Dd@Tn@Hb@@R@PDd@@PDT@d@@N@J@PBd@@L@R@NDl@@PBTDt@@TBRDd@@R@PFx@@R@Pf@nB@N@L@ZBLBp@BPc@lD{@TOB_@JMDa@HKBUOEUGg@AMCOAO]e@", "average_heartrate": null, "average_speed": 2.245145738657901, "streak": 1}, {"run_id": 9223370363627508407, "name": "run from keep", "distance": 2703.447887841259, "moving_time": "0:20:11", "type": "Run", "start_date": "2023-01-09 01:00:56", "start_date_local": "2023-01-08 18:00:56", "location_country": "{'latitude': 37.882061992789936, 'longitude': -122.29530294870936, 'country': '\u7f8e\u56fd', 'nationCode': '840', 'province': None, 'city': None, 'cityCode': None, 'district': None, 'districtCode': None}", "summary_polyline": "{qefFzpliVMw@C[Gs@e@g@SFg@JUFg@Lc@LQBu@ZQBa@LQ@aAb@i@F_@H[B[Je@Ru@PQBc@JSDa@JOBODa@HODQDa@JOBQDa@JOB]HMB]Ha@H_@J_@Hm@JOFOB]JOBSDe@J_@HO@OB_@HO@]J]DKBKB]Li@PODMBk@Lg@La@Bo@TQBQD_@HMB[FSFWFUDK@m@PKBKB[HMBMB[F[FMDKB]HKBOBi@LIHFh@Df@Hh@BRDb@BRBPNhALTz@W`@E\\MPEJG^MJCZCLERCZGPEd@KZGZCNE\\IJELGXIJAJE\\GJCJCf@ILELEZKNELAZGLENCZILCHAJCXINGtAYJELCHE|@OLCNCZGNCJEXCZKNGHCZIH?HAHCXGLEJALEZEJCNEVELELEXENENE\\IJENCl@Ix@U^KLCJCLCZGLEJEZGLALE\\ENGNC", "average_heartrate": null, "average_speed": 2.232409486243814, "streak": 1}, {"run_id": 9223370363286909107, "name": "run from keep", "distance": 2025.31237782842, "moving_time": "0:14:32", "type": "Run", "start_date": "2023-01-12 23:43:13", "start_date_local": "2023-01-12 16:43:13", "location_country": "{'latitude': 37.876823726575296, 'longitude': -122.29881623124088, 'country': '\u7f8e\u56fd', 'nationCode': '840', 'province': None, 'city': None, 'cityCode': None, 'district': None, 'districtCode': None}", "summary_polyline": "quefF~qliVUDk@J{@XSFkA\\QJHl@Fl@BRIfAF\\DRDf@@P^tCBVFn@BVLl@BRH~@DTHr@BVJp@BVJl@BRFd@DX@LJj@`@E~@SNINEl@Mb@MLAJCl@OLCLCh@^H`@@LBN@JH`@LhABP@PPvADTHp@@THd@Jp@Jb@BRHn@DTLE`@EZIJCJE\\G|Cs@NGz@l@Bl@?NBPj@ZPCF?p@SNENA^EPCLA`@KES?UCQAe@CQGc@EMGo@Ms@AMCMAII[?IAG?GAKAIAK?IGUIc@AKESEa@CMCQCOEe@AUCSMaA", "average_heartrate": null, "average_speed": 2.3226059378766286, "streak": 1}, {"run_id": 9223370362922135707, "name": "run from keep", "distance": 1633.9060923803836, "moving_time": "0:12:12", "type": "Run", "start_date": "2023-01-17 05:05:03", "start_date_local": "2023-01-16 22:05:03", "location_country": "{'latitude': 37.88073413445062, 'longitude': -122.29436205871792, 'country': '\u7f8e\u56fd', 'nationCode': '840', 'province': None, 'city': None, 'cityCode': None, 'district': None, 'districtCode': None}", "summary_polyline": "moefFdpliVj@KTCj@MVKl@KRGl@MRGh@IPGf@KREh@Mb@Mf@Kb@MPCb@KRCb@IPGd@M|@Q~@QRGj@MNCh@MNEf@MPCd@K^IPENEVGLEr@MLGLCl@QUFc@Ja@HSB[LM@OBo@LMFOB]JMBQB[FKDK@MB]HQBOB_@JODs@POBOB[H]H]Jc@FMBKF_@HMBMD_@HK@OB[HOD_@NODQBeAVOBIBUDG@IBa@HMDK@_@FEDIAE@QFI@IDGBG@G@UFIBI@I?GBG@ED??E?GBI@MFNp@?@?C?C??", "average_heartrate": null, "average_speed": 2.2321121480606334, "streak": 1}, {"run_id": 9223370362499307007, "name": "run from keep", "distance": 1494.4390597040087, "moving_time": "0:10:32", "type": "Run", "start_date": "2023-01-22 02:33:56", "start_date_local": "2023-01-21 19:33:56", "location_country": "{'latitude': 37.880713095868295, 'longitude': -122.29430717201562, 'country': '\u7f8e\u56fd', 'nationCode': '840', 'province': None, 'city': None, 'cityCode': None, 'district': None, 'districtCode': None}", "summary_polyline": "ulefFfoliVf@KPELCv@ORChASRGn@OTGd@Kd@KPEr@ORE`@KLCNEd@KNCNEb@KPEt@QPCPEFCg@FQBe@Ne@HMBa@JSDa@Je@JQFa@JUFw@RMBs@Lc@FQBy@RSDc@HSBe@LSDc@Le@JSDe@LUFWHVCNEb@KNCb@KNE`@KPENCn@OPCNE^KLENC^INCLC@?c@J]HK@a@FOB{AZYFk@JUFw@TM@GBG@C@QD@?KFG@GBGHDNBR", "average_heartrate": null, "average_speed": 2.3646187653544444, "streak": 1}, {"run_id": 9223370362070049007, "name": "run from keep", "distance": 1922.7923468091558, "moving_time": "0:13:04", "type": "Run", "start_date": "2023-01-27 01:45:27", "start_date_local": "2023-01-26 18:45:27", "location_country": "{'latitude': 37.8790815949315, 'longitude': -122.29353396810568, 'country': '\u7f8e\u56fd', 'nationCode': '840', 'province': None, 'city': None, 'cityCode': None, 'district': None, 'districtCode': None}", "summary_polyline": "qoefFbpliVj@Kt@KVEj@M~@[jAQXGnA]NIz@Od@GLEfAYf@GPEj@QRGlAW{@AUHc@HQDa@Ns@FODMBWFo@RQDkAXs@Nc@L_@Fe@POD{@RMBMD]Ba@DODK@]HMBOBc@HI^d@QpASJClBk@LANGj@GPE\\M^CLI^ILEJA\\KLGNC^E\\KLEJE~@KJCNA^KNE`@K^KHCn@Qa@Ds@P_@JKHuAVM@QB}@\\QF_@By@LWDaAZGBEBOF", "average_heartrate": null, "average_speed": 2.4525412586851476, "streak": 1}, {"run_id": 9223370360775188707, "name": "run from keep", "distance": 1638.1230264214246, "moving_time": "0:11:00", "type": "Run", "start_date": "2023-02-11 01:28:09", "start_date_local": "2023-02-10 18:28:09", "location_country": "{'latitude': 37.87858203232621, 'longitude': -122.29339466743438, 'country': '\u7f8e\u56fd', 'nationCode': '840', 'province': None, 'city': None, 'cityCode': None, 'district': None, 'districtCode': None}", "summary_polyline": "{oefFhpliVfAQXGn@OXGn@OTEp@OTGnBc@PGtAWTGXGPELCh@MTEb@Kh@MTGx@Qi@M{@RQBw@PQDiAXODKBs@NOFa@Fs@Xa@LQBe@HQ@wA`@a@L_APq@DMBAVNGl@INCPEd@MPCb@KNELCj@MPE^IVGJCHAZQp@Gb@KXGAB?A????C?@?@APENC`@ILENCZIQBKD[FKBGBWFSDG@]Ho@LMD", "average_heartrate": null, "average_speed": 2.4820045854870068, "streak": 1}, {"run_id": 9223370360171410207, "name": "run from keep", "distance": 2081.9855623577055, "moving_time": "0:13:59", "type": "Run", "start_date": "2023-02-18 01:08:46", "start_date_local": "2023-02-17 18:08:46", "location_country": "{'latitude': 37.88239686560012, 'longitude': -122.29367496987628, 'country': '\u7f8e\u56fd', 'nationCode': '840', 'province': None, 'city': None, 'cityCode': None, 'district': None, 'districtCode': None}", "summary_polyline": "gqefFbrliVxBqATIrCi@fA]jASl@MnA[RId@GPEfCi@RGi@Cs@NSF{@RODu@FQFqB|@[HOBODUFKBc@o@AUGi@AOCUKOaA\\a@HMBE@I@[HQDyAVe@PMBKBw@La@Nq@Fi@PODOB}@TMDMB_@HOBIBa@FOF}@RKB]FODQ@_@FMDQB_@JQHu@HQHa@NQDMB_@HOBa@By@Xk@HYLGCNE\\I`@Q`@KNENCx@[LCLGn@ALGfAGPEnBe@NELGl@ENCNE^INGPC", "average_heartrate": null, "average_speed": 2.481508417589637, "streak": 1}, {"run_id": 9223370359910880007, "name": "run from keep", "distance": 1163.9832270097413, "moving_time": "0:07:06", "type": "Run", "start_date": "2023-02-21 01:37:49", "start_date_local": "2023-02-20 18:37:49", "location_country": "{'latitude': 37.88002510768611, 'longitude': -122.2938365677678, 'country': '\u7f8e\u56fd', 'nationCode': '840', 'province': None, 'city': None, 'cityCode': None, 'district': None, 'districtCode': None}", "summary_polyline": "aqefFxpliVVE|@[r@QxCk@l@ITGj@ONC^MLENGZEd@GRCd@MREf@KREnA[RGhAUh@KTGf@KRGf@]UFiBVsAf@WBSDSBc@De@Hq@XOHOB_@HQBc@JOFK@a@HQDw@Lc@JOFqAVO@o@T", "average_heartrate": null, "average_speed": 2.7323549929806132, "streak": 1}, {"run_id": 9223370357666231507, "name": "run from keep", "distance": 961.7866907408028, "moving_time": "0:05:18", "type": "Run", "start_date": "2023-03-19 01:10:22", "start_date_local": "2023-03-18 18:10:22", "location_country": "{'latitude': 37.879813834714035, 'longitude': -122.29372534600343, 'country': '\u7f8e\u56fd', 'nationCode': '840', 'province': None, 'city': None, 'cityCode': None, 'district': None, 'districtCode': None}", "summary_polyline": "}oefF`pliVTEh@IRCh@MRGp@MrD_Ax@Qt@Mh@KPCj@KTIl@ORE|@SJANE\\KNCVQi@LS@_AVSH{@Tu@Pa@H{@Rc@JMDOD_@HK@KDK?o@PODw@J", "average_heartrate": null, "average_speed": 3.024486448870449, "streak": 1}, {"run_id": 9223370357146778707, "name": "run from keep", "distance": 1582.9523004541866, "moving_time": "0:09:05", "type": "Run", "start_date": "2023-03-25 01:24:12", "start_date_local": "2023-03-24 18:24:12", "location_country": "{'latitude': 37.880479258823634, 'longitude': -122.2940071167203, 'country': '\u7f8e\u56fd', 'nationCode': '840', 'province': None, 'city': None, 'cityCode': None, 'district': None, 'districtCode': None}", "summary_polyline": "koefFbpliVRGj@KPGl@GzBi@jAS`Dw@NCPC^IRENE`@ITGl@MPE|@Sv@QNEJEZGNCNCZINELCb@Il@STGJE\\GLCJEfAUg@C_ANQDeAV[Fw@PKDIBa@Do@XOFIFYHIDi@H_@FOFODe@HODMD{@JODc@Ru@LODODo@Pe@Ha@Lg@PQDa@HQ?w@Le@LUF", "average_heartrate": null, "average_speed": 2.9044996338608926, "streak": 1}, {"run_id": 9223370356555413707, "name": "run from keep", "distance": 1847.1030810375842, "moving_time": "0:11:33", "type": "Run", "start_date": "2023-03-31 21:37:49", "start_date_local": "2023-03-31 14:37:49", "location_country": "{'latitude': 37.88023866522816, 'longitude': -122.2939290936298, 'country': '\u7f8e\u56fd', 'nationCode': '840', 'province': None, 'city': None, 'cityCode': None, 'district': None, 'districtCode': None}", "summary_polyline": "avefFdrliVWHiBb@UDs@NeA\\UFeAHUDk@RWFi@LsA^_@J[DSHg@JQDe@JQDg@HSD_@LSBc@JSBg@LODc@?TEd@MREZGLGh@WNCJE`@KJAPE`@Il@ENCPEb@ILCNEj@y@Em@CoAJCXEn@MPEb@KPCNG\\IPCLE`@MNAb@KNG^ORC^KNCPG\\Id@UNEJCZGNCLEr@GPCNEn@M`@KfAKNENE`@IPCNE^EH?Lz@@NFb@a@z@OBc@LQBk@L", "average_heartrate": null, "average_speed": 2.665372411309645, "streak": 1}, {"run_id": 9223370356291310807, "name": "run from keep", "distance": 1528.279913511764, "moving_time": "0:08:22", "type": "Run", "start_date": "2023-04-03 23:02:35", "start_date_local": "2023-04-03 16:02:35", "location_country": "{'latitude': 37.88136789434824, 'longitude': -122.2933975201845, 'country': '\u7f8e\u56fd', 'nationCode': '840', 'province': None, 'city': None, 'cityCode': None, 'district': None, 'districtCode': None}", "summary_polyline": "gwefFprliVsAVy@PyCn@s@HU@i@NiBlBxAwAcAVw@XUDi@JUF}@HSBe@Li@LSDe@NqATMDu@VgAOMaBF]TKpA]RE~@Sz@Sh@KPIn@QPCt@MNCNE^IJCJCJCb@IbBa@PCd@MPCrA[REh@Qj@OREj@IfAU", "average_heartrate": null, "average_speed": 3.0443822978321995, "streak": 1}, {"run_id": 9223370355081638907, "name": "run from keep", "distance": 1026.76464777427, "moving_time": "0:06:09", "type": "Run", "start_date": "2023-04-17 23:06:07", "start_date_local": "2023-04-17 16:06:07", "location_country": "{'latitude': 37.88030212511357, 'longitude': -122.29394967314995, 'country': '\u7f8e\u56fd', 'nationCode': '840', 'province': None, 'city': None, 'cityCode': None, 'district': None, 'districtCode': None}", "summary_polyline": "ymefFjoliVt@Wr@QVGp@KZI^Gp@YNAv@Eb@If@K`@INEPC`AUTGf@MZId@MVCp@IMOu@H[HMBKD_ARa@HMDOB[HQBOFcANa@Vc@Tc@F_B^a@HMF_@Nc@L_AVI@IB", "average_heartrate": null, "average_speed": 2.7825600210684827, "streak": 1}, {"run_id": 9223370354566617307, "name": "run from keep", "distance": 1296.1493313054546, "moving_time": "0:08:12", "type": "Run", "start_date": "2023-04-23 22:07:41", "start_date_local": "2023-04-23 15:07:41", "location_country": "{'latitude': 37.88158451584724, 'longitude': -122.29427761846097, 'country': '\u7f8e\u56fd', 'nationCode': '840', 'province': None, 'city': None, 'cityCode': None, 'district': None, 'districtCode': None}", "summary_polyline": "auefFvqliVu@PoAVWFq@Pu@LWDeAPSDk@NUFi@Lk@Pi@JYHg@LMD]FQB]FOFOBiATSFe@Fa@DSHe@JODa@HQDa@JJNPCp@QJATGJCNCn@ONGNEfA_@NENC\\It@Q\\IPCLC^ILENGXEJEHAJCVG^KNEl@M\\EJC`@KNE`AQ~@WLC^I", "average_heartrate": null, "average_speed": 2.63444986037694, "streak": 1}, {"run_id": 9223370353785563007, "name": "run from keep", "distance": 1053.5586856723191, "moving_time": "0:06:38", "type": "Run", "start_date": "2023-05-02 23:06:54", "start_date_local": "2023-05-02 16:06:54", "location_country": "{'latitude': 37.8805681138051, 'longitude': -122.29405377016678, 'country': '\u7f8e\u56fd', 'nationCode': '840', 'province': None, 'city': None, 'cityCode': None, 'district': None, 'districtCode': None}", "summary_polyline": "aoefF|oliVTGh@ITEn@On@IVEhBm@RGz@Q|FgTqCfS^Kb@KNEdASj@MRC~@QPAHOy@HSDkAZSDu@Fi@VgALODa@Hw@PQBOF}@`@iA`@MFMD_@HMDMBYDMB[FSHUD", "average_heartrate": null, "average_speed": 2.647132376061103, "streak": 1}, {"run_id": 9223370352007468907, "name": "run from keep", "distance": 1454.7236540797437, "moving_time": "0:10:25", "type": "Run", "start_date": "2023-05-23 12:58:01", "start_date_local": "2023-05-23 20:58:01", "location_country": "{'latitude': 39.899167366149136, 'longitude': 116.24161276191782, 'country': '\u4e2d\u56fd', 'nationCode': '156', 'province': '\u5317\u4eac\u5e02', 'city': '\u5317\u4eac\u5e02', 'cityCode': '010', 'district': '\u77f3\u666f\u5c71\u533a', 'districtCode': '110107'}", "summary_polyline": "mjprFqnldUXz@JLJNZb@d@ELJz@y@Eg@SuADc@?EAB@DDEm@s@OCQEe@E[S@m@ROh@DNAf@?b@JHFT?JCLE\\GZ?FCJDLAV?VBJ?t@BPAt@CXAd@FdAHl@C\\BJBZ?LAh@Cn@@HBL?J?|ASLAN@t@u@BgBAc@Bk@BUB]Gm@a@}@_@Ac@o@@OAqAAS@k@eAg@aAf@OH", "average_heartrate": null, "average_speed": 2.32755784652759, "streak": 1}, {"run_id": 9223370351575536107, "name": "run from keep", "distance": 1685.3211418615588, "moving_time": "0:10:41", "type": "Run", "start_date": "2023-05-28 12:55:54", "start_date_local": "2023-05-28 20:55:54", "location_country": "{'latitude': 39.90029381764511, 'longitude': 116.24056229520403, 'country': '\u4e2d\u56fd', 'nationCode': '156', 'province': '\u5317\u4eac\u5e02', 'city': '\u5317\u4eac\u5e02', 'cityCode': '010', 'district': '\u77f3\u666f\u5c71\u533a', 'districtCode': '110107'}", "summary_polyline": null, "average_heartrate": null, "average_speed": 2.6292061495500136, "streak": 1}, {"run_id": 9223370351314737207, "name": "run from keep", "distance": 1130.1952133192674, "moving_time": "0:06:59", "type": "Run", "start_date": "2023-05-31 13:25:04", "start_date_local": "2023-05-31 21:25:04", "location_country": "{'latitude': 39.8977727086517, 'longitude': 116.24040717522372, 'country': '\u4e2d\u56fd', 'nationCode': '156', 'province': '\u5317\u4eac\u5e02', 'city': '\u5317\u4eac\u5e02', 'cityCode': '010', 'district': '\u77f3\u666f\u5c71\u533a', 'districtCode': '110107'}", "summary_polyline": null, "average_heartrate": null, "average_speed": 2.6973632776116165, "streak": 1}, {"run_id": 9223370350965351907, "name": "run from keep", "distance": 1435.0770735576439, "moving_time": "0:09:10", "type": "Run", "start_date": "2023-06-04 14:27:52", "start_date_local": "2023-06-04 22:27:52", "location_country": "{'latitude': 39.89821954655947, 'longitude': 116.23833863692063, 'country': '\u4e2d\u56fd', 'nationCode': '156', 'province': '\u5317\u4eac\u5e02', 'city': '\u5317\u4eac\u5e02', 'cityCode': '010', 'district': '\u77f3\u666f\u5c71\u533a', 'districtCode': '110107'}", "summary_polyline": null, "average_heartrate": null, "average_speed": 2.60923104283208, "streak": 1}, {"run_id": 9223370346654827007, "name": "run from keep", "distance": 519.060037288479, "moving_time": "0:02:52", "type": "Run", "start_date": "2023-07-24 11:56:16", "start_date_local": "2023-07-24 19:56:16", "location_country": "{'latitude': 31.228259346826572, 'longitude': 121.40494865661988, 'country': '\u4e2d\u56fd', 'nationCode': '156', 'province': '\u4e0a\u6d77\u5e02', 'city': '\u4e0a\u6d77\u5e02', 'cityCode': '021', 'district': '\u666e\u9640\u533a', 'districtCode': '310107'}", "summary_polyline": null, "average_heartrate": null, "average_speed": 3.0177909144679007, "streak": 1}, {"run_id": 9223370345350057507, "name": "run from keep", "distance": 1676.9010146703008, "moving_time": "0:11:50", "type": "Run", "start_date": "2023-08-08 14:13:23", "start_date_local": "2023-08-08 22:13:23", "location_country": "{'latitude': 31.228123353016304, 'longitude': 121.40423809454188, 'country': '\u4e2d\u56fd', 'nationCode': '156', 'province': '\u4e0a\u6d77\u5e02', 'city': '\u4e0a\u6d77\u5e02', 'cityCode': '021', 'district': '\u666e\u9640\u533a', 'districtCode': '310107'}", "summary_polyline": null, "average_heartrate": null, "average_speed": 2.3618324150285925, "streak": 1}]